prj_tree/__init__.py
prj_tree/cli.py
prj_tree/config.py
prj_tree/core.py
prj_tree/ignore.py
prj_tree/render_ascii.py
prj_tree/render_html.py
prj_tree/render_json.py
prj_tree/render_md.py
prj_tree/utils.py
prj_tree-0.1.2.dist-info/METADATA
prj_tree-0.1.2.dist-info/WHEEL
prj_tree-0.1.2.dist-info/entry_points.txt
prj_tree-0.1.2.dist-info/RECORD
