Metadata-Version: 2.4
Name: prj-tree
Version: 0.1.2
Summary: Project tree extractor with ignore support, flexible includes, and multiple renderers (HTML/MD/JSON/ASCII).
Project-URL: Homepage, https://pypi.org/project/prj-tree/
Project-URL: Repository, https://github.com/his-name-anton/prj-tree
Author: Anton Larin
License: MIT
Keywords: cli,html,json,markdown,project,structure,tools,tree
Classifier: Development Status :: 3 - Alpha
Classifier: Intended Audience :: Developers
Classifier: License :: OSI Approved :: MIT License
Classifier: Programming Language :: Python
Classifier: Programming Language :: Python :: 3
Classifier: Programming Language :: Python :: 3.9
Classifier: Programming Language :: Python :: 3.10
Classifier: Programming Language :: Python :: 3.11
Classifier: Programming Language :: Python :: 3.12
Classifier: Topic :: Utilities
Requires-Python: >=3.9
Requires-Dist: tomli; python_version < '3.11'
